producetracker/__init__.py
producetracker/app.py
producetracker/categories.db
producetracker/database.py
producetracker/enhance.py
producetracker/expirations.db
producetracker/installer.py
producetracker/matching.py
producetracker/scraper.py
producetracker/storagetypes.db
producetracker/style.kv
producetracker/subcategories.db
producetracker/test_database.py
producetracker/useritems.db
producetracker/utilities.py
producetracker/resources/about_icon.png
producetracker/resources/alph_sort_icon.png
producetracker/resources/apple_icon.png
producetracker/resources/apple_icon_colored.png
producetracker/resources/brown_apple_icon.png
producetracker/resources/cancel_icon.png
producetracker/resources/capture_icon.png
producetracker/resources/eraser_icon.png
producetracker/resources/expired_sort_icon.png
producetracker/resources/flip_icon.png
producetracker/resources/light_icon.png
producetracker/resources/light_icon_colored.png
producetracker/resources/plus_icon.png
producetracker/resources/receipt_icon.png
producetracker/resources/red_apple_icon.png
producetracker/resources/search_icon.png
producetracker/resources/settings_icon.png
producetracker/resources/submit_icon.png
BAproducetracker-2.3.0.dist-info/METADATA
BAproducetracker-2.3.0.dist-info/WHEEL
BAproducetracker-2.3.0.dist-info/entry_points.txt
BAproducetracker-2.3.0.dist-info/top_level.txt
BAproducetracker-2.3.0.dist-info/RECORD
