Metadata-Version: 2.1
Name: BAproducetracker
Version: 2.3.0
Summary: Produce expiration tracker
Home-page: https://github.com/jd3builds/BadApplesJJP
Author: Brody, Joseph // Dillon, John // Estrada, Pablo
License: UNKNOWN
Platform: UNKNOWN
Requires-Python: >=3.8
Requires-Dist: Kivy (==2.0.0rc3)
Requires-Dist: Kivy-Garden (==0.1.4)
Requires-Dist: Pillow (==7.2.0)
Requires-Dist: Pygments (==2.7.1)
Requires-Dist: certifi (==2020.6.20)
Requires-Dist: chardet (==3.0.4)
Requires-Dist: docutils (==0.16)
Requires-Dist: idna (==2.10)
Requires-Dist: pip (==20.2.3)
Requires-Dist: requests (==2.24.0)
Requires-Dist: setuptools (==47.1.0)
Requires-Dist: urllib3 (==1.25.10)
Requires-Dist: plyer (==1.4.3)
Requires-Dist: pytesseract (==0.3.6)
Requires-Dist: opencv-python (==4.4.0.44)
Requires-Dist: Cython (==0.29.21)
Requires-Dist: Jinja2 (==2.11.2)
Requires-Dist: Kivy-examples (==2.0.0rc3)
Requires-Dist: MarkupSafe (==1.1.1)
Requires-Dist: appdirs (==1.4.4)
Requires-Dist: bs4 (==0.0.1)
Requires-Dist: beautifulsoup4 (==4.9.3)
Requires-Dist: autoconf (==0.6.2)
Requires-Dist: colorama (==0.4.3)
Requires-Dist: importlib-metadata (==2.0.0)
Requires-Dist: pep517 (==0.6.0)
Requires-Dist: python-for-android (==2020.6.2)
Requires-Dist: pytoml (==0.1.21)
Requires-Dist: sh (==1.14.0)
Requires-Dist: six (==1.15.0)
Requires-Dist: soupsieve (==2.0.1)
Requires-Dist: toml (==0.10.1)
Requires-Dist: wheel (==0.35.1)
Requires-Dist: zipp (==3.3.0)
